Workbook

Sheet Historical
A1: Historical Financials (€m)
A2: Financial Key Figures | B2: 2023 | C2: 2024 | D2: 2025 | E2: Notes
A3: Revenue | B3: 15382 | C3: 17295 | D3: 18822 | E3: Total company sales for period | F3: Operating
A4: COGS | B4: 14099 | C4: 15238 | D4: 16325 | E4: Direct production and delivery costs
A5: Gross Profit | B5: =B3-B4 -> 1283 | C5: =C3-C4 -> 2057 | D5: =D3-D4 -> 2497 | E5: Revenue - COGS
A7: Opex | B7: =B5-B8 -> 194 | C7: =C5-C8 -> 452 | D7: =D5-D8 -> 444 | E7: Opex excluding production costs | F7: Profitability
A8: EBITDA | B8: 1089 | C8: 1605 | D8: 2053 | E8: Operating profit before D&A
A10: Depreciation & Amortization | B10: =B8-B11 -> 797 | C10: =C8-C11 -> 811 | D10: =D8-D11 -> 1038
A11: EBIT | B11: 292 | C11: 794 | D11: 1015 | E11: Operating profit after D&A
A13: Taxes | B13: 214 | C13: 300 | D13: 259 | E13: Tax expense based on pre-tax profit
A14: Net Income | B14: 78 | C14: 494 | D14: 780 | E14: Profit after all expenses and taxes
A16: Capex | B16: 457 | C16: 670 | D16: 821 | E16: Investmanets in property, plant, equipment | F16: Cash
A17: Interest-bearing position (net) | B17: 32 | C17: 809 | D17: 1174 | E17: Net interest-bearing debt (annual report) | F17: Capital structure

Sheet Assumptions 
A1: Assumptions Vestas (€m)
A2: Financial Key Figures | B2: 2025A | C2: 2026E | D2: 2027E | E2: 2028E | F2: 2029E | G2: Notes
A3: Deliveries MW | B3: 14537 | C3: 15200 | D3: 16000 | E3: 16800 | F3: 17500 | G3: MW Delivered (Annual Report) | H3: Revenue Assumptions
A4: Average Selling Price | B4: =Historical!D3/'Assumptions '!B3 -> 1.2947651 | C4: 1.3 | D4: 1.31 | E4: 1.32 | F4: 1.33 | G4: Revenue divided by MW delivered
A5: Revenue Growth % | B5: =(Historical!D3-Historical!C3)/Historical!C3 -> 0.088291414 | C5: 0.05 | D5: 0.061 | E5: 0.058 | F5: 0.05 | G5: Implied from revenue derived as Deliveries * ASP
A6: Gross Margin % | B6: =Historical!D5/Historical!D3 -> 0.1326639 | C6: 0.138 | D6: 0.143 | E6: 0.148 | F6: 0.152 | G6: Gross Profit / Revenue (Annual Report) | H6: Profitability Assumptions
A7: Opex % Revenue | B7: =Historical[[#This Row],[2025]]/Historical!D3 -> 0.023589417 | C7: 0.023 | D7: 0.022 | E7: 0.021 | F7: 0.02 | G7: Calculated as (Gross Profit - EBITDA) / Revenue
A8: Depreciation & Amortization % | B8: =Historical!D10/Historical!D3 -> 0.055148231 | C8: 0.054 | D8: 0.053 | E8: 0.052 | F8: 0.051 | G8: (EBITDA - EBIT) / Revenue
A9: ∆ Net Working Capital % | B9: -0.0441 | C9: -0.04 | D9: -0.035 | E9: -0.03 | F9: -0.025 | G9: (NWC 2025 - NWC 2024) / Revenue | H9: Operating Assumptions
A10: Capex % Revenue | B10: =Historical!D16/Historical!D3 -> 0.043619169 | C10: 0.045 | D10: 0.044 | E10: 0.043 | F10: 0.042 | G10: Capex modeled as % of revenue, gradually decreasing due to efficiency gains
A11: Tax Rate % | B11: =Historical!D13/(Historical!D13+Historical!D14) -> 0.24927815 | C11: 0.25 | D11: 0.25 | E11: 0.25 | F11: 0.25 | G11: Income Tax / Profit Before Tax | H11: Tax Assumptions
A12: WACC | B12: 0.08 | C12: 0.08 | D12: 0.08 | E12: 0.08 | F12: 0.08 | G12: Estimated based on CAPM and European industrial peer discount rates | H12: Valuation Assumptions
A13: Terminal Growth | B13: 0.02 | C13: 0.02 | D13: 0.02 | E13: 0.02 | F13: 0.02 | G13: Based on long term Inflation and mature industrial growth expectations

Sheet P&L
A1: P&L Vestas (€m)
A2: Financial Key Figures | B2: 2025A | C2: 2026E | D2: 2027E | E2: 2028E | F2: 2029E | G2: Notes
A3: Revenue | B3: =Historical[[#This Row],[2025]] -> 18822 | C3: =Assumptions[[#This Row],[2026E]]*'Assumptions '!C4 -> 19760 | D3: =Assumptions[[#This Row],[2027E]]*'Assumptions '!D4 -> 20960 | E3: =Assumptions[[#This Row],[2028E]]*'Assumptions '!E4 -> 22176 | F3: =Assumptions[[#This Row],[2029E]]*'Assumptions '!F4 -> 23275 | G3: Calculated as Deliveries * ASP
A4: COGS | B4: =Historical[[#This Row],[2025]] -> 16325 | C4: =C3*(1-'Assumptions '!C6) -> 17033.12 | D4: =D3*(1-'Assumptions '!D6) -> 17962.72 | E4: =E3*(1-'Assumptions '!E6) -> 18893.952 | F4: =F3*(1-'Assumptions '!F6) -> 19737.2 | G4: Derived from revenue and gross margin assumptions
A5: Gross Profit | B5: =Historical[[#This Row],[2025]] -> 2497 | C5: =C3-C4 -> 2726.88 | D5: =D3-D4 -> 2997.28 | E5: =E3-E4 -> 3282.048 | F5: =F3-F4 -> 3537.8 | G5: Revenue - COGS
A7: Opex | B7: =Historical[[#This Row],[2025]] -> 444 | C7: =C3*Assumptions[[#This Row],[2026E]] -> 454.48 | D7: =D3*Assumptions[[#This Row],[2027E]] -> 461.12 | E7: =E3*Assumptions[[#This Row],[2028E]] -> 465.696 | F7: =F3*Assumptions[[#This Row],[2029E]] -> 465.5 | G7: Opex estimated as a percentage of revenue
A8: EBITDA | B8: =Historical[[#This Row],[2025]] -> 2053 | C8: =C5-C7 -> 2272.4 | D8: =D5-D7 -> 2536.16 | E8: =E5-E7 -> 2816.352 | F8: =F5-F7 -> 3072.3 | G8: Gross Profit - Opex
A10: Depreciation & Amortization | B10: =Historical[[#This Row],[2025]] -> 1038 | C10: =C3*'Assumptions '!C8 -> 1067.04 | D10: =D3*'Assumptions '!D8 -> 1110.88 | E10: =E3*'Assumptions '!E8 -> 1153.152 | F10: =F3*'Assumptions '!F8 -> 1187.025 | G10: Estimated as a percentage of revenue based on historical levels
A11: EBIT | B11: =Historical[[#This Row],[2025]] -> 1015 | C11: =C8-C10 -> 1205.36 | D11: =D8-D10 -> 1425.28 | E11: =E8-E10 -> 1663.2 | F11: =F8-F10 -> 1885.275 | G11: EBITDA - Depreciation & Amortization
A13: Taxes | B13: =Historical[[#This Row],[2025]] -> 259 | C13: =C11*'Assumptions '!C11 -> 301.34 | D13: =D11*'Assumptions '!D11 -> 356.32 | E13: =E11*'Assumptions '!E11 -> 415.8 | F13: =F11*'Assumptions '!F11 -> 471.31875 | G13: Historical 2025A reported; forecast years based on constant effective tax rate
A14: Net Income | B14: =Historical[[#This Row],[2025]] -> 780 | C14: =C11-C13 -> 904.02 | D14: =D11-D13 -> 1068.96 | E14: =E11-E13 -> 1247.4 | F14: =F11-F13 -> 1413.9562 | G14: EBIT - taxes

Sheet Cash Flow
A1: Cash Flow Vestas (€m)
A2: Financial Key Figures | B2: 2025A | C2: 2026E | D2: 2027E | E2: 2028E | F2: 2029E | G2: Notes
A3: EBIT | B3: ='P&L'!B11 -> 1015 | C3: ='P&L'!C11 -> 1205.36 | D3: ='P&L'!D11 -> 1425.28 | E3: ='P&L'!E11 -> 1663.2 | F3: ='P&L'!F11 -> 1885.275 | G3: From P&L
A4: Tax | B4: ='P&L'!B13 -> 259 | C4: ='P&L'!C13 -> 301.34 | D4: ='P&L'!D13 -> 356.32 | E4: ='P&L'!E13 -> 415.8 | F4: ='P&L'!F13 -> 471.31875 | G4: From P&L / based on effective tax rate
A5: NOPAT | B5: =B3-B4 -> 756 | C5: =C3-C4 -> 904.02 | D5: =D3-D4 -> 1068.96 | E5: =E3-E4 -> 1247.4 | F5: =F3-F4 -> 1413.9562 | G5: EBIT after tax
A7: D&A | B7: ='P&L'!B10 -> 1038 | C7: ='P&L'!C10 -> 1067.04 | D7: ='P&L'!D10 -> 1110.88 | E7: ='P&L'!E10 -> 1153.152 | F7: ='P&L'!F10 -> 1187.025 | G7: Non-cash expense added back
A8: Capex | B8: =Historical!D16 -> 821 | C8: ='P&L'!C3*'Assumptions '!C10 -> 889.2 | D8: ='P&L'!D3*'Assumptions '!D10 -> 922.24 | E8: ='P&L'!E3*'Assumptions '!E10 -> 953.568 | F8: ='P&L'!F3*'Assumptions '!F10 -> 977.55 | G8: % of revenue assumption
A9: ∆NWC | B9: =ABS('P&L'!B3*Assumptions[[#This Row],[2025A]]) -> 830.0502 | C9: =ABS('P&L'!C3*Assumptions[[#This Row],[2026E]]) -> 790.4 | D9: =ABS('P&L'!D3*Assumptions[[#This Row],[2027E]]) -> 733.6 | E9: =ABS('P&L'!E3*Assumptions[[#This Row],[2028E]]) -> 665.28 | F9: =ABS('P&L'!F3*Assumptions[[#This Row],[2029E]]) -> 581.875 | G9: Change in working capital
A11: Free Cash Flow | B11: =B5+B7-B8-B9 -> 142.9498 | C11: =C5+C7-C8-C9 -> 291.46 | D11: =D5+D7-D8-D9 -> 524 | E11: =E5+E7-E8-E9 -> 781.704 | F11: =F5+F7-F8-F9 -> 1041.5562 | G11: Cash available to investors

Sheet DCF 
A1: Discounted Cash Flow Vestas (€m)
A2: Financial Key Figures | B2: 2026E | C2: 2027E | D2: 2028E | E2: 2029E | F2: Value | G2: Notes
A3: Free Cash Flow | B3: ='Cash Flow'!C11 -> 291.46 | C3: ='Cash Flow'!D11 -> 524 | D3: ='Cash Flow'!E11 -> 781.704 | E3: ='Cash Flow'!F11 -> 1041.5562 | G3: From Cash Flow statement (NOPAT + D&A - Capes - ∆NWC)
A4: Discount Factor | B4: =1/(1+'Assumptions '!B12)^(COLUMN()-COLUMN($B$2)+1) -> 0.92592593 | C4: =1/(1+'Assumptions '!C12)^(COLUMN()-COLUMN($B$2)+1) -> 0.85733882 | D4: =1/(1+'Assumptions '!D12)^(COLUMN()-COLUMN($B$2)+1) -> 0.79383224 | E4: =1/(1+'Assumptions '!E12)^(COLUMN()-COLUMN($B$2)+1) -> 0.73502985 | G4: Discounted using WACC (8%) over forcast period
A5: Present Value FCF | B5: =B3*B4 -> 269.87037 | C5: =C3*C4 -> 449.24554 | D5: =D3*D4 -> 620.54184 | E5: =E3*E4 -> 765.57494 | G5: FCF discounted to present value using WACC
A7: Terminal Value | E7: =E3*(1+'Assumptions '!B13)/('Assumptions '!B12-'Assumptions '!B13) -> 17706.456 | G7: Calculated using Gordon Growth Model (g=2%)
A8: PV Terminal Value | E8: =E7*E4 -> 13014.774 | G8: Terminal vallue discounted to present value
A10: Enterprise Value | F10: =SUM(B5:E5)+E8 -> 15120.007 | G10: Sum of discounted cash flows and terminal value
A11: Net Debt | F11: =Historical!D17 -> 1174 | G11: Latest reported net interest-bearing position (2025)
A12: Equity Value | F12: =F10-F11 -> 13946.007 | G12: Enterprise Value minus Net Debt
